python_elastic_logstash/__init__.py
python_elastic_logstash-2.0.0.dist-info/LICENSE
python_elastic_logstash-2.0.0.dist-info/METADATA
python_elastic_logstash-2.0.0.dist-info/WHEEL
python_elastic_logstash-2.0.0.dist-info/top_level.txt
python_elastic_logstash-2.0.0.dist-info/RECORD
