Metadata-Version: 2.1
Name: python-elastic-logstash
Version: 2.0.0
Summary: Python logging handler for elastic search.
Home-page: https://github.com/washim/python-elastic-logstash
Author: Washim Ahmed
Author-email: washim.ahmed@gmail.com
License: MIT
Platform: UNKNOWN
Classifier: Development Status :: 5 - Production/Stable
Classifier: Intended Audience :: Developers
Classifier: License :: OSI Approved :: MIT License
Classifier: Operating System :: OS Independent
Classifier: Programming Language :: Python :: 3
Classifier: Topic :: Internet :: WWW/HTTP
Classifier: Topic :: Software Development :: Libraries :: Python Modules
Classifier: Topic :: System :: Logging
Requires-Python: >=3
